autora/experiment_runner/synthetic/utilities.py
autora/experiment_runner/synthetic/abstract/lmm.py
autora/experiment_runner/synthetic/abstract/template_experiment.py
autora/experiment_runner/synthetic/economics/expected_value_theory.py
autora/experiment_runner/synthetic/economics/prospect_theory.py
autora/experiment_runner/synthetic/neuroscience/task_switching.py
autora/experiment_runner/synthetic/psychology/exp_learning.py
autora/experiment_runner/synthetic/psychology/luce_choice_ratio.py
autora/experiment_runner/synthetic/psychology/q_learning.py
autora/experiment_runner/synthetic/psychophysics/stevens_power_law.py
autora/experiment_runner/synthetic/psychophysics/weber_fechner_law.py
autora_synthetic-2.2.0.dist-info/LICENSE
autora_synthetic-2.2.0.dist-info/METADATA
autora_synthetic-2.2.0.dist-info/WHEEL
autora_synthetic-2.2.0.dist-info/top_level.txt
autora_synthetic-2.2.0.dist-info/RECORD
