Metadata-Version: 2.1
Name: autora-synthetic
Version: 2.2.0
Summary: AutoRA Synthetic Experiments
License: MIT License
Project-URL: homepage, http://www.empiricalresearch.ai
Project-URL: repository, https://github.com/AutoResearch/autora-synthetic
Project-URL: documentation, https://autoresearch.github.io/autora-synthetic/
License-File: LICENSE
Requires-Dist: autora-core
Provides-Extra: dev
Requires-Dist: autora-synthetic[test]; extra == "dev"
Requires-Dist: autora-core[dev]; extra == "dev"
Requires-Dist: autora-workflow; extra == "dev"
Requires-Dist: scikit-learn; extra == "dev"
Provides-Extra: test
Requires-Dist: pytest; extra == "test"
Requires-Dist: hypothesis; extra == "test"
